django_info_pages-0.0.5.dist-info/DESCRIPTION.rst
django_info_pages-0.0.5.dist-info/METADATA
django_info_pages-0.0.5.dist-info/RECORD
django_info_pages-0.0.5.dist-info/WHEEL
django_info_pages-0.0.5.dist-info/metadata.json
django_info_pages-0.0.5.dist-info/top_level.txt
info/__init__.py
info/admin.py
info/autocomplete_light_registry.py
info/migration_helpers.py
info/models.py
info/tests.py
info/views.py
info/fixtures/bar.png
info/fixtures/sample_blog_posts.json
info/migrations/0001_initial.py
info/migrations/0002_datetimefield_remove_default.py
info/migrations/__init__.py
info/static/info/js/admin.js
info/templates/info/_blog_open_graph.html
info/templates/info/_pagination.html
info/templates/info/blog_list.html
info/templates/info/blog_post.html
info/templates/info/infopage_detail.html
info/urls/__init__.py
info/urls/blog.py
info/urls/pages.py
