Metadata-Version: 2.0
Name: django-info-pages
Version: 0.0.5
Summary: Editable info pages and basic blog functionality for Django
Home-page: https://github.com/mysociety/django-info-pages
Author: Edmund von der Burg
Author-email: evdb@ecclestoad.co.uk
License: AGPL
Keywords: django blog cms
Platform: UNKNOWN
Requires-Dist: Django (>=1.8.12,<1.9)
Requires-Dist: beautifulsoup4
Requires-Dist: lxml
Requires-Dist: Markdown
Requires-Dist: django-markitup
Requires-Dist: nose
Requires-Dist: django-autocomplete-light (==2.3.3)
Requires-Dist: django-file-archive (==0.0.2)
Requires-Dist: django-pagination (==1.0.7)
Requires-Dist: django-slug-helpers (>=0.0.3)
Provides-Extra: test
Requires-Dist: mock; extra == 'test'
